{"size":6767205,"files":[{"id":"0f0f54ea-49cc-4425-ac91-4af4faa0d476","file":"CAM00679(1).jpg","width":"1536","height":"2048","date":"2013:04:22 08:45:37","thumbnail":null,"size":149078},{"id":"5c7d9a4d-e283-4f1b-ba88-14339aca8eba","file":"CAM00679.jpg","width":"3264","height":"2448","date":"2013:04:22 08:45:37","thumbnail":null,"size":328177},{"id":"0e35c082-d862-4562-9674-0d7fad824a38","file":"CAM00678(1).jpg","width":"1536","height":"2048","date":"2013:04:22 08:45:35","thumbnail":null,"size":198079},{"id":"b4fefd8e-0dfd-4926-b49c-f4adb0e734d1","file":"CAM00678.jpg","width":"3264","height":"2448","date":"2013:04:22 08:45:35","thumbnail":null,"size":381345},{"id":"51e46d3f-2ed9-41d8-a978-99f7fab08615","file":"CAM00677(1).jpg","width":"1536","height":"2048","date":"2013:04:22 08:44:59","thumbnail":null,"size":189959},{"id":"2a3bafff-dc7a-4df3-8cfe-94380c6b3602","file":"CAM00677.jpg","width":"3264","height":"2448","date":"2013:04:22 08:44:59","thumbnail":null,"size":430289},{"id":"59f648c7-69a7-40e0-a0f3-8601709463b3","file":"CAM00676(1).jpg","width":"1536","height":"2048","date":"2013:04:22 08:44:56","thumbnail":null,"size":280994},{"id":"996f50bc-f1a3-4fca-83c8-c69b7f37fd3b","file":"CAM00676.jpg","width":"3264","height":"2448","date":"2013:04:22 08:44:56","thumbnail":null,"size":589263},{"id":"159513e3-bed3-4e47-9d9c-27264a874f8e","file":"CAM00674(1).jpg","width":"3264","height":"2448","date":"2013:04:22 08:44:47","thumbnail":null,"size":321864},{"id":"8ec5dca4-09a6-48be-a057-128a9fd58108","file":"CAM00674.jpg","width":"1536","height":"2048","date":"2013:04:22 08:44:47","thumbnail":null,"size":177849},{"id":"9a327cb0-b992-47bc-97d4-f126979664b9","file":"CAM00673(1).jpg","width":"3264","height":"2448","date":"2013:04:22 08:44:45","thumbnail":null,"size":320348},{"id":"614e67ef-98e4-4fbc-893f-010217bfc37e","file":"CAM00673.jpg","width":"1536","height":"2048","date":"2013:04:22 08:44:45","thumbnail":null,"size":166957},{"id":"4b76233e-bbe2-4e34-93a5-ac00af6f6a19","file":"CAM00672(1).jpg","width":"1536","height":"2048","date":"2013:04:22 08:44:40","thumbnail":null,"size":156985},{"id":"97987906-e907-4d24-8a30-0db28e46537f","file":"CAM00672.jpg","width":"3264","height":"2448","date":"2013:04:22 08:44:40","thumbnail":null,"size":275946},{"id":"2604f03b-b602-4814-9b63-8340df75dc1e","file":"CAM00671(1).jpg","width":"1536","height":"2048","date":"2013:04:22 08:44:30","thumbnail":null,"size":180682},{"id":"798f9cdb-3c15-4c7e-855b-45a5b4d3d0ba","file":"CAM00671.jpg","width":"3264","height":"2448","date":"2013:04:22 08:44:30","thumbnail":null,"size":385222},{"id":"a622e02b-2a24-4c2c-997f-2637ff775c3c","file":"CAM00670(1).jpg","width":"1536","height":"2048","date":"2013:04:22 08:44:18","thumbnail":null,"size":148456},{"id":"59dce70b-ec82-4abf-8235-c1ec915c7c92","file":"CAM00670.jpg","width":"3264","height":"2448","date":"2013:04:22 08:44:18","thumbnail":null,"size":279770},{"id":"995ffec2-6674-4019-8dd6-12dab77d51ec","file":"CAM00669(1).jpg","width":"1536","height":"2048","date":"2013:04:22 08:44:15","thumbnail":null,"size":135814},{"id":"0ada805e-1f8f-4440-bc52-ba565a49f3c3","file":"CAM00669.jpg","width":"3264","height":"2448","date":"2013:04:22 08:44:15","thumbnail":null,"size":247184},{"id":"c2c087c7-c15b-4b1e-a290-be7e368a09e9","file":"CAM00668(1).jpg","width":"3264","height":"2448","date":"2013:04:22 08:43:59","thumbnail":null,"size":442594},{"id":"b351188b-3fc7-4965-ad8e-667cf9501560","file":"CAM00668.jpg","width":"1536","height":"2048","date":"2013:04:22 08:43:59","thumbnail":null,"size":193773},{"id":"addea7a4-d3ca-4386-9254-4cbc9931bd50","file":"CAM00667(1).jpg","width":"1536","height":"2048","date":"2013:04:22 08:43:58","thumbnail":null,"size":241125},{"id":"49ca2671-f8bc-43d9-9a0d-429ee0e43f39","file":"CAM00667.jpg","width":"3264","height":"2448","date":"2013:04:22 08:43:58","thumbnail":null,"size":545452}],"image_count":24,"video_count":0,"heic_count":0,"youtube_count":0}